odoo8_addon_l10n_be_mis_reports-8.0.1.0.0.99.dev7-py2.7-nspkg.pth
odoo8_addon_l10n_be_mis_reports-8.0.1.0.0.99.dev7.dist-info/METADATA
odoo8_addon_l10n_be_mis_reports-8.0.1.0.0.99.dev7.dist-info/RECORD
odoo8_addon_l10n_be_mis_reports-8.0.1.0.0.99.dev7.dist-info/WHEEL
odoo8_addon_l10n_be_mis_reports-8.0.1.0.0.99.dev7.dist-info/namespace_packages.txt
odoo8_addon_l10n_be_mis_reports-8.0.1.0.0.99.dev7.dist-info/top_level.txt
odoo_addons/l10n_be_mis_reports/README.rst
odoo_addons/l10n_be_mis_reports/__init__.py
odoo_addons/l10n_be_mis_reports/__openerp__.py
odoo_addons/l10n_be_mis_reports/data/mis_report_bs.xml
odoo_addons/l10n_be_mis_reports/data/mis_report_pl.xml
odoo_addons/l10n_be_mis_reports/i18n/fr.po
odoo_addons/l10n_be_mis_reports/i18n/l10n_be_mis_reports.pot
odoo_addons/l10n_be_mis_reports/i18n/nl.po
odoo_addons/l10n_be_mis_reports/static/description/icon.png
